jobs/__init__.py
jobs/api.py
jobs/conftest.py
jobs/migrations.py
jobs/utils.py
jobs/worker.py
jobs/tests/__init__.py
jobs/tests/fixtures.py
jobs/tests/task.py
jobs/tests/test_api.py
jobs/tests/test_process.py
jobs/tests/test_worker.py
jobs/tests/utils.py
pgjobs-0.2.1.dist-info/LICENSE.txt
pgjobs-0.2.1.dist-info/METADATA
pgjobs-0.2.1.dist-info/WHEEL
pgjobs-0.2.1.dist-info/entry_points.txt
pgjobs-0.2.1.dist-info/top_level.txt
pgjobs-0.2.1.dist-info/RECORD
