Metadata-Version: 2.1
Name: pgjobs
Version: 0.2.1
Summary: Postgresql job scheduling
Home-page: https://github.com/vinissimus/jobs
Author: jordi collell
Author-email: jordic@gmail.com
License: UNKNOWN
Platform: UNKNOWN
Requires-Dist: asyncpg (<0.21,>=0.20.1)
Provides-Extra: test
Requires-Dist: pytest ; extra == 'test'
Requires-Dist: pytest-asyncio ; extra == 'test'
Requires-Dist: pytest-cov ; extra == 'test'
Requires-Dist: pytest-docker-fixtures[pg] ; extra == 'test'
Requires-Dist: coverage ; extra == 'test'
